Workbook

Sheet Cover
B2: SUN PHARMA / ORGANON
B3: Valuation Model — Chapter 7
B4: All-cash acquisition · $14.00/share · EV ~$11.75bn
B6: KEY OUTPUTS
B7: Enterprise value ($mm) | C7: =DCF!C21 -> 12382.623
B8: Equity value ($mm) | C8: =DCF!C23 -> 4282.6226
B9: Equity value per share ($) | C9: =DCF!C25 -> 16.471625
B10: Offer price ($/share) | C10: =DCF!C26 -> 14
B11: Premium/(discount) to offer | C11: =DCF!C27 -> 0.17654467
B12: WACC (base) | C12: =Assumptions!C27 -> 0.0900325
B14: COLOUR LEGEND
B15: Blue = input / assumption
B16: Black = formula
B17: Green = link to another sheet
B19: Confidential — prepared for educational purposes only. Analyst estimates; see report Ch.7 for sources.

Sheet Assumptions
B2: Sun Pharma / Organon — Valuation Model
B3: Assumptions (blue = input, black = formula, green = link)
B5: OPERATING ASSUMPTIONS
B6: Base revenue FY2025 ($mm) | C6: 6216
B7: EBITDA margin (%) | C7: 0.3
B8: D&A ($mm) | C8: 300
B9: Capex ($mm) | C9: 160
B10: Change in NWC ($mm) | C10: 40
B11: Tax rate (%) | C11: 0.19
B12: Terminal exit EV/EBITDA (x) | C12: 6
C13: 2026 | D13: 2027 | E13: 2028 | F13: 2029 | G13: 2030
B14: Revenue growth by year | C14: -0.02 | D14: -0.01 | E14: 0 | F14: 0.01 | G14: 0.01
B16: WACC BUILD
B17: Risk-free rate (US 10-yr) | C17: 0.045
B18: Equity risk premium | C18: 0.055
B19: Beta (levered) | C19: 1.05
B20: Cost of equity (CAPM) | C20: =C17+C19*C18 -> 0.10275
B21: Pre-tax cost of debt | C21: 0.07
B22: After-tax cost of debt | C22: =C21*(1-C11) -> 0.0567
B23: Weight of equity | C23: 0.65
B24: Weight of debt | C24: 0.35
B25: WACC (CAPM) | C25: =C23*C20+C24*C22 -> 0.0866325
B26: Company-specific premium | C26: 0.0034
B27: WACC (base case) | C27: =C25+C26 -> 0.0900325
B29: CAPITALIZATION
B30: Shares outstanding (mm) | C30: 260
B31: Net debt ($mm) | C31: 8100
B32: Offer price ($/share) | C32: 14
B34: Note: analyst assumptions anchored on FY2025 actuals; see report Ch.7.

Sheet DCF
B2: Discounted Cash Flow
B3: US$ mm | C3: 2026 | D3: 2027 | E3: 2028 | F3: 2029 | G3: 2030
B4: Period | C4: 1 | D4: 2 | E4: 3 | F4: 4 | G4: 5
B5: Revenue | C5: =Assumptions!$C$6*(1+Assumptions!C14) -> 6091.68 | D5: =C5*(1+Assumptions!D14) -> 6030.7632 | E5: =D5*(1+Assumptions!E14) -> 6030.7632 | F5: =E5*(1+Assumptions!F14) -> 6091.0708 | G5: =F5*(1+Assumptions!G14) -> 6151.9815
B6: EBITDA | C6: =C5*Assumptions!$C$7 -> 1827.504 | D6: =D5*Assumptions!$C$7 -> 1809.229 | E6: =E5*Assumptions!$C$7 -> 1809.229 | F6: =F5*Assumptions!$C$7 -> 1827.3212 | G6: =G5*Assumptions!$C$7 -> 1845.5945
B7: less: D&A | C7: =-Assumptions!$C$8 -> -300 | D7: =-Assumptions!$C$8 -> -300 | E7: =-Assumptions!$C$8 -> -300 | F7: =-Assumptions!$C$8 -> -300 | G7: =-Assumptions!$C$8 -> -300
B8: EBIT | C8: =C6+C7 -> 1527.504 | D8: =D6+D7 -> 1509.229 | E8: =E6+E7 -> 1509.229 | F8: =F6+F7 -> 1527.3212 | G8: =G6+G7 -> 1545.5945
B9: NOPAT | C9: =C8*(1-Assumptions!$C$11) -> 1237.2782 | D9: =D8*(1-Assumptions!$C$11) -> 1222.4755 | E9: =E8*(1-Assumptions!$C$11) -> 1222.4755 | F9: =F8*(1-Assumptions!$C$11) -> 1237.1302 | G9: =G8*(1-Assumptions!$C$11) -> 1251.9315
B10: add: D&A | C10: =Assumptions!$C$8 -> 300 | D10: =Assumptions!$C$8 -> 300 | E10: =Assumptions!$C$8 -> 300 | F10: =Assumptions!$C$8 -> 300 | G10: =Assumptions!$C$8 -> 300
B11: less: Capex | C11: =-Assumptions!$C$9 -> -160 | D11: =-Assumptions!$C$9 -> -160 | E11: =-Assumptions!$C$9 -> -160 | F11: =-Assumptions!$C$9 -> -160 | G11: =-Assumptions!$C$9 -> -160
B12: less: Change in NWC | C12: =-Assumptions!$C$10 -> -40 | D12: =-Assumptions!$C$10 -> -40 | E12: =-Assumptions!$C$10 -> -40 | F12: =-Assumptions!$C$10 -> -40 | G12: =-Assumptions!$C$10 -> -40
B13: Unlevered FCF | C13: =C9+C10+C11+C12 -> 1337.2782 | D13: =D9+D10+D11+D12 -> 1322.4755 | E13: =E9+E10+E11+E12 -> 1322.4755 | F13: =F9+F10+F11+F12 -> 1337.1302 | G13: =G9+G10+G11+G12 -> 1351.9315
B14: Discount factor | C14: =1/(1+Assumptions!$C$27)^C4 -> 0.91740384 | D14: =1/(1+Assumptions!$C$27)^D4 -> 0.8416298 | E14: =1/(1+Assumptions!$C$27)^E4 -> 0.77211441 | F14: =1/(1+Assumptions!$C$27)^F4 -> 0.70834073 | G14: =1/(1+Assumptions!$C$27)^G4 -> 0.6498345
B15: PV of UFCF | C15: =C13*C14 -> 1226.8242 | D15: =D13*D14 -> 1113.0348 | E15: =E13*E14 -> 1021.1024 | F15: =F13*F14 -> 947.14379 | G15: =G13*G14 -> 878.53174
B17: DCF SUMMARY
B18: Sum PV of UFCF (2026–30) | C18: =SUM(C15:G15) -> 5186.6368
B19: Terminal value (exit x EBITDA30) | C19: =Assumptions!$C$12*G6 -> 11073.567
B20: PV of terminal value | C20: =C19*G14 -> 7195.9857
B21: Enterprise value | C21: =C18+C20 -> 12382.623
B22: less: Net debt | C22: =-Assumptions!$C$31 -> -8100
B23: Equity value | C23: =C21+C22 -> 4282.6226
B24: Shares (mm) | C24: =Assumptions!$C$30 -> 260
B25: Equity value per share | C25: =C23/C24 -> 16.471625
B26: Offer price ($/share) | C26: =Assumptions!$C$32 -> 14
B27: Premium/(discount) to offer | C27: =C25/C26-1 -> 0.17654467

Sheet Sensitivity
B2: DCF Sensitivity — Equity Value / Share ($)
B4: Exit x \ WACC | C4: 0.08 | D4: 0.085 | E4: 0.09 | F4: 0.095 | G4: 0.1
B5: 5 | C5: =(SUMPRODUCT(DCF!$C$13:$G$13,(1+C$4)^(-DCF!$C$4:$G$4))+$B5*DCF!$G$6*(1+C$4)^(-5)-Assumptions!$C$31)/Assumptions!$C$30 -> 13.481497 | D5: =(SUMPRODUCT(DCF!$C$13:$G$13,(1+D$4)^(-DCF!$C$4:$G$4))+$B5*DCF!$G$6*(1+D$4)^(-5)-Assumptions!$C$31)/Assumptions!$C$30 -> 12.662425 | E5: =(SUMPRODUCT(DCF!$C$13:$G$13,(1+E$4)^(-DCF!$C$4:$G$4))+$B5*DCF!$G$6*(1+E$4)^(-5)-Assumptions!$C$31)/Assumptions!$C$30 -> 11.863938 | F5: =(SUMPRODUCT(DCF!$C$13:$G$13,(1+F$4)^(-DCF!$C$4:$G$4))+$B5*DCF!$G$6*(1+F$4)^(-5)-Assumptions!$C$31)/Assumptions!$C$30 -> 11.085412 | G5: =(SUMPRODUCT(DCF!$C$13:$G$13,(1+G$4)^(-DCF!$C$4:$G$4))+$B5*DCF!$G$6*(1+G$4)^(-5)-Assumptions!$C$31)/Assumptions!$C$30 -> 10.326245
B6: 5.5 | C6: =(SUMPRODUCT(DCF!$C$13:$G$13,(1+C$4)^(-DCF!$C$4:$G$4))+$B6*DCF!$G$6*(1+C$4)^(-5)-Assumptions!$C$31)/Assumptions!$C$30 -> 15.897036 | D6: =(SUMPRODUCT(DCF!$C$13:$G$13,(1+D$4)^(-DCF!$C$4:$G$4))+$B6*DCF!$G$6*(1+D$4)^(-5)-Assumptions!$C$31)/Assumptions!$C$30 -> 15.022817 | E6: =(SUMPRODUCT(DCF!$C$13:$G$13,(1+E$4)^(-DCF!$C$4:$G$4))+$B6*DCF!$G$6*(1+E$4)^(-5)-Assumptions!$C$31)/Assumptions!$C$30 -> 14.170688 | F6: =(SUMPRODUCT(DCF!$C$13:$G$13,(1+F$4)^(-DCF!$C$4:$G$4))+$B6*DCF!$G$6*(1+F$4)^(-5)-Assumptions!$C$31)/Assumptions!$C$30 -> 13.339975 | G6: =(SUMPRODUCT(DCF!$C$13:$G$13,(1+G$4)^(-DCF!$C$4:$G$4))+$B6*DCF!$G$6*(1+G$4)^(-5)-Assumptions!$C$31)/Assumptions!$C$30 -> 12.530031
B7: 6 | C7: =(SUMPRODUCT(DCF!$C$13:$G$13,(1+C$4)^(-DCF!$C$4:$G$4))+$B7*DCF!$G$6*(1+C$4)^(-5)-Assumptions!$C$31)/Assumptions!$C$30 -> 18.312576 | D7: =(SUMPRODUCT(DCF!$C$13:$G$13,(1+D$4)^(-DCF!$C$4:$G$4))+$B7*DCF!$G$6*(1+D$4)^(-5)-Assumptions!$C$31)/Assumptions!$C$30 -> 17.38321 | E7: =(SUMPRODUCT(DCF!$C$13:$G$13,(1+E$4)^(-DCF!$C$4:$G$4))+$B7*DCF!$G$6*(1+E$4)^(-5)-Assumptions!$C$31)/Assumptions!$C$30 -> 16.477437 | F7: =(SUMPRODUCT(DCF!$C$13:$G$13,(1+F$4)^(-DCF!$C$4:$G$4))+$B7*DCF!$G$6*(1+F$4)^(-5)-Assumptions!$C$31)/Assumptions!$C$30 -> 15.594538 | G7: =(SUMPRODUCT(DCF!$C$13:$G$13,(1+G$4)^(-DCF!$C$4:$G$4))+$B7*DCF!$G$6*(1+G$4)^(-5)-Assumptions!$C$31)/Assumptions!$C$30 -> 14.733818
B8: 6.5 | C8: =(SUMPRODUCT(DCF!$C$13:$G$13,(1+C$4)^(-DCF!$C$4:$G$4))+$B8*DCF!$G$6*(1+C$4)^(-5)-Assumptions!$C$31)/Assumptions!$C$30 -> 20.728116 | D8: =(SUMPRODUCT(DCF!$C$13:$G$13,(1+D$4)^(-DCF!$C$4:$G$4))+$B8*DCF!$G$6*(1+D$4)^(-5)-Assumptions!$C$31)/Assumptions!$C$30 -> 19.743602 | E8: =(SUMPRODUCT(DCF!$C$13:$G$13,(1+E$4)^(-DCF!$C$4:$G$4))+$B8*DCF!$G$6*(1+E$4)^(-5)-Assumptions!$C$31)/Assumptions!$C$30 -> 18.784187 | F8: =(SUMPRODUCT(DCF!$C$13:$G$13,(1+F$4)^(-DCF!$C$4:$G$4))+$B8*DCF!$G$6*(1+F$4)^(-5)-Assumptions!$C$31)/Assumptions!$C$30 -> 17.849101 | G8: =(SUMPRODUCT(DCF!$C$13:$G$13,(1+G$4)^(-DCF!$C$4:$G$4))+$B8*DCF!$G$6*(1+G$4)^(-5)-Assumptions!$C$31)/Assumptions!$C$30 -> 16.937604
B9: 7 | C9: =(SUMPRODUCT(DCF!$C$13:$G$13,(1+C$4)^(-DCF!$C$4:$G$4))+$B9*DCF!$G$6*(1+C$4)^(-5)-Assumptions!$C$31)/Assumptions!$C$30 -> 23.143655 | D9: =(SUMPRODUCT(DCF!$C$13:$G$13,(1+D$4)^(-DCF!$C$4:$G$4))+$B9*DCF!$G$6*(1+D$4)^(-5)-Assumptions!$C$31)/Assumptions!$C$30 -> 22.103995 | E9: =(SUMPRODUCT(DCF!$C$13:$G$13,(1+E$4)^(-DCF!$C$4:$G$4))+$B9*DCF!$G$6*(1+E$4)^(-5)-Assumptions!$C$31)/Assumptions!$C$30 -> 21.090936 | F9: =(SUMPRODUCT(DCF!$C$13:$G$13,(1+F$4)^(-DCF!$C$4:$G$4))+$B9*DCF!$G$6*(1+F$4)^(-5)-Assumptions!$C$31)/Assumptions!$C$30 -> 20.103664 | G9: =(SUMPRODUCT(DCF!$C$13:$G$13,(1+G$4)^(-DCF!$C$4:$G$4))+$B9*DCF!$G$6*(1+G$4)^(-5)-Assumptions!$C$31)/Assumptions!$C$30 -> 19.14139
B11: Offer price $14.00/share. Shaded region (higher WACC / lower exit) covers the offer.

Sheet Trading Comps
B2: Trading Comparables
B4: Organon FY25 Adj. EBITDA ($mm) | C4: 1910
B6: Peer | C6: EV/EBITDA
B7: Viatris | C7: 6
B8: Teva | C8: 7.2
B9: Hikma | C9: 7.8
B10: Dr Reddy's | C10: 11
B11: Cipla | C11: 12.5
B13: Median (Western: Viatris/Teva/Hikma) | C13: =MEDIAN(C7:C9) -> 7.2
B14: Relevant range — low (x) | C14: 6
B15: Relevant range — high (x) | C15: 7.5
B17: Implied EV — low ($mm) | C17: =C14*C4 -> 11460
B18: Implied EV — high ($mm) | C18: =C15*C4 -> 14325
B19: Implied equity/share — low ($) | C19: =(C17-Assumptions!$C$31)/Assumptions!$C$30 -> 12.923077
B20: Implied equity/share — high ($) | C20: =(C18-Assumptions!$C$31)/Assumptions!$C$30 -> 23.942308
B22: Peer multiples illustrative/approx.; tie to latest filings. Indian peers (premium) excluded from range.

Sheet Precedents
B2: Precedent Transactions
B4: Organon FY25 Adj. EBITDA ($mm) | C4: ='Trading Comps'!C4 -> 1910
B6: Precedent | C6: EV/EBITDA
B7: Mylan + Upjohn → Viatris (2020) | C7: 5.5
B8: STADA / Bain-Cinven (2017) | C8: 8
B9: Teva / Allergan Generics (2016) | C9: 10
B11: Relevant range — low (x) | C11: 7
B12: Relevant range — high (x) | C12: 9
B14: Implied EV — low ($mm) | C14: =C11*C4 -> 13370
B15: Implied EV — high ($mm) | C15: =C12*C4 -> 17190
B16: Implied equity/share — low ($) | C16: =(C14-Assumptions!$C$31)/Assumptions!$C$30 -> 20.269231
B17: Implied equity/share — high ($) | C17: =(C15-Assumptions!$C$31)/Assumptions!$C$30 -> 34.961538
B19: Precedent multiples approximate; growth/scarcity in precedents overstates a declining asset.

Sheet Football Field
B2: Football Field — Equity Value / Share ($)
B4: Methodology | C4: Low | D4: High
B5: DCF (WACC 8.5–9.5%, exit 5.5–6.5x) | C5: =Sensitivity!F6 -> 13.339975 | D5: =Sensitivity!D8 -> 19.743602
B6: Trading comps (6.0–7.5x) | C6: ='Trading Comps'!C19 -> 12.923077 | D6: ='Trading Comps'!C20 -> 23.942308
B7: Precedent txns (7.0–9.0x) | C7: =Precedents!C16 -> 20.269231 | D7: =Precedents!C17 -> 34.961538
B8: 52-week trading range | C8: 9 | D8: 22
B10: Offer price ($/share) | C10: =Assumptions!$C$32 -> 14
