Workbook

Sheet Cover
B2: SUN PHARMA / ORGANON
B3: Merger Model — Chapter 8
B4: All-cash · new debt ~$9.5bn · no shares issued
B6: KEY OUTPUTS
B7: Year-1 EPS accretion | C7: =Accretion!C17 -> 0.59542254
B8: Year-3 EPS accretion | C8: =Accretion!E17 -> 0.75070423
B9: Pro forma EPS Yr1 (₹) | C9: =Accretion!C16 -> 72.658786
B10: Goodwill created ($mm) | C10: =PPA!C9 -> 1330
B11: Net leverage at close (x) | C11: =Debt_Schedule!C11 -> 2.037037
B12: Net leverage Yr5 (x) | C12: =Debt_Schedule!G11 -> 0.1242236
B14: COLOUR LEGEND
B15: Blue = input
B16: Black = formula
B17: Green = link to another sheet
B19: Confidential — educational purposes only. Analyst estimates; see report Ch.8.

Sheet Assumptions
B2: Sun Pharma / Organon — Merger Model
B3: Assumptions (blue = input, black = formula, green = link)
B5: INPUTS
B6: FX (INR per USD) | C6: 85.5
B7: Sun net income ($mm) | C7: 1278
B8: Sun shares outstanding (mm) | C8: 2399.3
B9: Sun EBITDA ($mm) | C9: 1765
B10: Organon adj. net income ($mm) | C10: 954
B11: Organon existing interest, pre-tax ($mm) | C11: 450
B12: Organon EBITDA ($mm) | C12: 1910
B13: New acquisition debt ($mm) | C13: 9500
B14: Blended debt rate (%) | C14: 0.06
B15: Sun cash used ($mm) | C15: 2250
B16: Forgone rate on cash (%) | C16: 0.04
B17: Synergy run-rate ($mm) | C17: 350
B18: Synergy phasing (Yr1 / Yr2 / Yr3) | C18: 0.3 | D18: 0.7 | E18: 1
B19: PPA intangible step-up ($mm) | C19: 2000
B20: Intangible life (years) | C20: 15
B21: Tax rate (%) | C21: 0.19
B22: FCF for debt sweep ($mm/yr) | C22: 1800
B23: Organon book equity ($mm) | C23: 700
B24: Equity purchase price ($mm) | C24: 3650

Sheet Sources_Uses
B2: Sources & Uses ($mm)
B4: Sources | D4: Uses
B5: New acquisition debt | C5: =Assumptions!C13 -> 9500 | D5: Refinance Organon debt | E5: 8100
B6: Sun internal accruals | C6: =Assumptions!C15 -> 2250 | D6: Equity consideration | E6: =Assumptions!C24 -> 3650
B7: Organon balance-sheet cash | C7: 250 | D7: Fees & expenses (est.) | E7: 250
B8: Total sources | C8: =SUM(C5:C7) -> 12000 | D8: Total uses | E8: =SUM(E5:E7) -> 12000
B10: Check (sources − uses) | C10: =C8-E8 -> 0

Sheet PPA
B2: Purchase Price Allocation ($mm)
B4: Equity purchase price | C4: =Assumptions!C24 -> 3650
B5: less: Organon book equity | C5: =-Assumptions!C23 -> -700
B6: Allocable excess | C6: =C4+C5 -> 2950
B7: Identifiable intangible step-up | C7: =Assumptions!C19 -> 2000
B8: Deferred tax liability on step-up | C8: =C7*Assumptions!C21 -> 380
B9: Goodwill (plug) | C9: =C6-C7+C8 -> 1330
B11: Incremental amortization, pre-tax | C11: =C7/Assumptions!C20 -> 133.33333
B12: Incremental amortization, after-tax | C12: =C11*(1-Assumptions!C21) -> 108
B14: Simplified PPA; book equity & step-up are analyst estimates. Goodwill not amortized (no EPS impact).

Sheet Debt_Schedule
B2: Debt Schedule ($mm)
B4: Year | C4: Yr 1 | D4: Yr 2 | E4: Yr 3 | F4: Yr 4 | G4: Yr 5
B5: Beginning debt | C5: =Assumptions!C13 -> 9500 | D5: =C9 -> 7700 | E5: =D9 -> 5900 | F5: =E9 -> 4100 | G5: =F9 -> 2300
B6: Interest (opening × rate) | C6: =C5*Assumptions!$C$14 -> 570 | D6: =D5*Assumptions!$C$14 -> 462 | E6: =E5*Assumptions!$C$14 -> 354 | F6: =F5*Assumptions!$C$14 -> 246 | G6: =G5*Assumptions!$C$14 -> 138
B7: FCF sweep (repayment) | C7: =-MIN(Assumptions!$C$22,C5) -> -1800 | D7: =-MIN(Assumptions!$C$22,D5) -> -1800 | E7: =-MIN(Assumptions!$C$22,E5) -> -1800 | F7: =-MIN(Assumptions!$C$22,F5) -> -1800 | G7: =-MIN(Assumptions!$C$22,G5) -> -1800
B8: Synergy phasing EBITDA add | C8: =Assumptions!$C$17*Assumptions!C18 -> 105 | D8: =Assumptions!$C$17*Assumptions!D18 -> 245 | E8: =Assumptions!$C$17*Assumptions!E18 -> 350 | F8: =Assumptions!$C$17*Assumptions!E18 -> 350 | G8: =Assumptions!$C$17*Assumptions!E18 -> 350
B9: Ending debt | C9: =C5+C7 -> 7700 | D9: =D5+D7 -> 5900 | E9: =E5+E7 -> 4100 | F9: =F5+F7 -> 2300 | G9: =G5+G7 -> 500
B10: Combined EBITDA | C10: =Assumptions!$C$9+Assumptions!$C$12+C8 -> 3780 | D10: =Assumptions!$C$9+Assumptions!$C$12+D8 -> 3920 | E10: =Assumptions!$C$9+Assumptions!$C$12+E8 -> 4025 | F10: =Assumptions!$C$9+Assumptions!$C$12+F8 -> 4025 | G10: =Assumptions!$C$9+Assumptions!$C$12+G8 -> 4025
B11: Net debt / EBITDA | C11: =C9/C10 -> 2.037037 | D11: =D9/D10 -> 1.505102 | E11: =E9/E10 -> 1.0186335 | F11: =F9/F10 -> 0.57142857 | G11: =G9/G10 -> 0.1242236
B13: Interest on opening balance (no circularity). FCF sweep flat; illustrative.

Sheet Accretion
B2: Accretion / (Dilution) Analysis ($mm unless noted)
C4: Year 1 | D4: Year 2 | E4: Year 3
B5: Sun standalone net income | C5: =Assumptions!$C$7 -> 1278 | D5: =Assumptions!$C$7 -> 1278 | E5: =Assumptions!$C$7 -> 1278
B6: Organon pre-financing earnings (a-t) | C6: =Assumptions!$C$10+Assumptions!$C$11*(1-Assumptions!$C$21) -> 1318.5 | D6: =Assumptions!$C$10+Assumptions!$C$11*(1-Assumptions!$C$21) -> 1318.5 | E6: =Assumptions!$C$10+Assumptions!$C$11*(1-Assumptions!$C$21) -> 1318.5
B7: less: new acquisition interest (a-t) | C7: =-Assumptions!$C$13*Assumptions!$C$14*(1-Assumptions!$C$21) -> -461.7 | D7: =-Assumptions!$C$13*Assumptions!$C$14*(1-Assumptions!$C$21) -> -461.7 | E7: =-Assumptions!$C$13*Assumptions!$C$14*(1-Assumptions!$C$21) -> -461.7
B8: less: forgone interest on cash (a-t) | C8: =-Assumptions!$C$15*Assumptions!$C$16*(1-Assumptions!$C$21) -> -72.9 | D8: =-Assumptions!$C$15*Assumptions!$C$16*(1-Assumptions!$C$21) -> -72.9 | E8: =-Assumptions!$C$15*Assumptions!$C$16*(1-Assumptions!$C$21) -> -72.9
B9: less: incremental PPA amort (a-t) | C9: =-PPA!C12 -> -108 | D9: =-PPA!C12 -> -108 | E9: =-PPA!C12 -> -108
B10: add: synergies (a-t) | C10: =Assumptions!$C$17*Assumptions!C18*(1-Assumptions!$C$21) -> 85.05 | D10: =Assumptions!$C$17*Assumptions!D18*(1-Assumptions!$C$21) -> 198.45 | E10: =Assumptions!$C$17*Assumptions!E18*(1-Assumptions!$C$21) -> 283.5
B11: Pro forma net income | C11: =SUM(C5:C10) -> 2038.95 | D11: =SUM(D5:D10) -> 2152.35 | E11: =SUM(E5:E10) -> 2237.4
B13: Sun standalone EPS ($) | C13: =Assumptions!$C$7/Assumptions!$C$8 -> 0.53265536 | D13: =Assumptions!$C$7/Assumptions!$C$8 -> 0.53265536 | E13: =Assumptions!$C$7/Assumptions!$C$8 -> 0.53265536
B14: Pro forma EPS ($) | C14: =C11/Assumptions!$C$8 -> 0.84981036 | D14: =D11/Assumptions!$C$8 -> 0.89707415 | E14: =E11/Assumptions!$C$8 -> 0.93252199
B15: Sun standalone EPS (₹) | C15: =C13*Assumptions!$C$6 -> 45.542033 | D15: =D13*Assumptions!$C$6 -> 45.542033 | E15: =E13*Assumptions!$C$6 -> 45.542033
B16: Pro forma EPS (₹) | C16: =C14*Assumptions!$C$6 -> 72.658786 | D16: =D14*Assumptions!$C$6 -> 76.69984 | E16: =E14*Assumptions!$C$6 -> 79.73063
B17: Accretion / (dilution) % | C17: =C14/C13-1 -> 0.59542254 | D17: =D14/D13-1 -> 0.68415493 | E17: =E14/E13-1 -> 0.75070423
B19: New interest held at opening $9.5bn (conservative; deleveraging upside not credited). Cross-border: INR acquirer, USD target at FX above.
