Workbook

Sheet Sun_Pharma
B2: Sun Pharma — Five-Year Financials
B4: INR crore (Mar-YE) | C4: FY21 | D4: FY22 | E4: FY23 | F4: FY24 | G4: FY25
B5: Revenue | C5: 33498 | D5: 38654 | E5: 43279 | F5: 48497 | G5: 52041
B6: EBITDA | C6: 8040 | D6: 9664 | E6: 11647 | F6: 13337 | G6: 15092
B7: EBITDA margin | C7: =C6/C5 -> 0.24001433 | D7: =D6/D5 -> 0.25001294 | E7: =E6/E5 -> 0.26911435 | F7: =F6/F5 -> 0.2750067 | G7: =G6/G5 -> 0.29000211
B8: Net profit | C8: 2904 | D8: 3273 | E8: 8474 | F8: 9576 | G8: 10929
B9: Net margin | C9: =C8/C5 -> 0.086691743 | D9: =D8/D5 -> 0.08467429 | E9: =E8/E5 -> 0.19579935 | F9: =F8/F5 -> 0.19745551 | G9: =G8/G5 -> 0.21000749
B10: Revenue growth (YoY) | D10: =D5/C5-1 -> 0.15391964 | E10: =E5/D5-1 -> 0.11965127 | F10: =F5/E5-1 -> 0.12056656 | G10: =G5/F5-1 -> 0.073076685
B12: Revenue CAGR FY21–FY25 | C12: =(G5/C5)^(1/4)-1 -> 0.11643049
B14: EBITDA FY21/FY22/FY24 approx (rev×est margin); FY23 & FY25 reported. Tie to annual reports.

Sheet Organon
B2: Organon — Five-Year Financials
B4: US$ mm (Dec-YE) | C4: 2021 | D4: 2022 | E4: 2023 | F4: 2024 | G4: 2025
B5: Revenue | C5: 6304 | D5: 6174 | E5: 6263 | F5: 6403 | G5: 6216
B6: Adj. EBITDA | C6: 2270 | D6: 2100 | E6: 1900 | F6: 1960 | G6: 1910
B7: Adj. EBITDA margin | C7: =C6/C5 -> 0.36008883 | D7: =D6/D5 -> 0.34013605 | E7: =E6/E5 -> 0.30336899 | F7: =F6/F5 -> 0.30610651 | G7: =G6/G5 -> 0.30727156
B8: GAAP net income | C8: n/a | D8: n/a | E8: 1027 | F8: 864 | G8: 187
B9: FCF before one-time | C9: n/a | D9: 875 | E9: 1000 | F9: 967 | G9: 900
B10: Revenue growth (YoY) | D10: =D5/C5-1 -> -0.020621827 | E10: =E5/D5-1 -> 0.01441529 | F10: =F5/E5-1 -> 0.022353505 | G10: =G5/F5-1 -> -0.02920506
B11: Gross debt | C11: 9134 | D11: 8913 | E11: 8900 | F11: 8880 | G11: 8640
B12: Cash | C12: 737 | D12: 706 | E12: 650 | F12: 690 | G12: 574
B13: Net debt | C13: =C11-C12 -> 8397 | D13: =D11-D12 -> 8207 | E13: =E11-E12 -> 8250 | F13: =F11-F12 -> 8190 | G13: =G11-G12 -> 8066
B14: Net debt / Adj. EBITDA | C14: =C13/C6 -> 3.6991189 | D14: =D13/D6 -> 3.9080952 | E14: =E13/E6 -> 4.3421053 | F14: =F13/F6 -> 4.1785714 | G14: =G13/G6 -> 4.2230366
B16: Adj. EBITDA 2021–22 estimated; 2023–25 reported. GAAP NI 2021–22 n/a (confirm 10-K).

Sheet Ratios
B2: Comparative Ratios — FY2025
B4: Metric | C4: Sun Pharma | D4: Organon
B5: Revenue growth (YoY) | C5: =Sun_Pharma!G10 -> 0.073076685 | D5: =Organon!G10 -> -0.02920506
B6: EBITDA margin | C6: =Sun_Pharma!G7 -> 0.29000211 | D6: =Organon!G7 -> 0.30727156
B7: Net debt / EBITDA | C7: =-Sun_Pharma!G6*0+(-1.7) -> -1.7 | D7: =Organon!G14 -> 4.2230366
B8: FCF before one-time ($mm) | C8: n/a (INR reporter) | D8: =Organon!G9 -> 900
B10: Sun net leverage shown as ~(1.7x) net cash (INR reporter; illustrative). Organon linked from sheet.
